ae/dev_ops.py
ae_dev_ops-0.3.9.dist-info/licenses/LICENSE.md
ae_dev_ops-0.3.9.dist-info/METADATA
ae_dev_ops-0.3.9.dist-info/WHEEL
ae_dev_ops-0.3.9.dist-info/top_level.txt
ae_dev_ops-0.3.9.dist-info/zip-safe
ae_dev_ops-0.3.9.dist-info/RECORD
